tunaapi/__init__.py
tunaapi/test.py
tunaapi/api/__init__.py
tunaapi/api/base.py
tunaapi/api/exceptions.py
tunaapi/api/utils.py
tunaapi/api/methods/__init__.py
tunaapi/api/methods/base.py
tunaapi/api/methods/get_tunnels.py
tunaapi/api/types/__init__.py
tunaapi/api/types/base.py
tunaapi/api/types/member_short.py
tunaapi/api/types/tunnel.py
tunaapi/api/types/user_api_key.py
tunaapi/http_cli/__init__.py
tunaapi/http_cli/base.py
tunaapi/http_cli/exceptions.py
tunaapi-0.1.dist-info/licenses/LICENSE
tunaapi-0.1.dist-info/METADATA
tunaapi-0.1.dist-info/WHEEL
tunaapi-0.1.dist-info/top_level.txt
tunaapi-0.1.dist-info/RECORD
