Metadata-Version: 2.4
Name: tunaapi
Version: 0.1
License-File: LICENSE
Requires-Dist: anyio~=4.9.0
Requires-Dist: certifi~=2025.4.26
Requires-Dist: h11~=0.16.0
Requires-Dist: httpcore~=1.0.9
Requires-Dist: httpx~=0.28.1
Requires-Dist: idna~=3.10
Requires-Dist: sniffio~=1.3.1
Dynamic: description
Dynamic: description-content-type
Dynamic: license-file
Dynamic: requires-dist
